ba63usb/__init__.py
ba63usb-0.2.dist-info/LICENSE
ba63usb-0.2.dist-info/METADATA
ba63usb-0.2.dist-info/WHEEL
ba63usb-0.2.dist-info/top_level.txt
ba63usb-0.2.dist-info/RECORD
