Metadata-Version: 2.2
Name: ba63usb
Version: 0.2
Summary: Python interface for Nixdorf BA63 USB HID display
Author: Yannick Richter
Project-URL: Homepage, https://github.com/Ultrawipf/ba63usb
Classifier: Programming Language :: Python :: 3
Classifier: License :: OSI Approved :: MIT License
Classifier: Operating System :: OS Independent
Requires-Python: >=3.8
License-File: LICENSE
Requires-Dist: hidapi
